code_print/__init__.py
code_print/libs/__init__.py
code_print/libs/click_order.py
code_print/libs/print_dir.py
code_print-0.1.0.dist-info/METADATA
code_print-0.1.0.dist-info/WHEEL
code_print-0.1.0.dist-info/entry_points.txt
code_print-0.1.0.dist-info/RECORD
