Metadata-Version: 2.1
Name: code-print
Version: 0.1.0
Summary: 
Author: David Cho
Author-email: csi00700@gmail.com
Requires-Python: >=3.11,<4.0
Classifier: Programming Language :: Python :: 3
Classifier: Programming Language :: Python :: 3.11
Classifier: Programming Language :: Python :: 3.12
Requires-Dist: click (>=8.1.7,<9.0.0)
